{
    "trends": {
        "Amazon stock": [],
        "NFL Honors": [],
        "Liverpool vs Tottenham": [],
        "Invincible season 3": [],
        "Barcelona": [],
        "Virginia McCaskey": [],
        "Caris LeVert": [],
        "Apple Cider Vinegar": [],
        "Bill Belichick girlfriend": [],
        "P.J. Tucker": [],
        "FC Barcelona": [],
        "Marcus Smart": [],
        "Adan Manzano": [],
        "Sweet Magnolias": [],
        "Joe Burrow": [],
        "Lil Wayne": [],
        "Eli Manning": [],
        "Kevin Porter Jr": [],
        "Kings": [],
        "Duke": []
    },
    "datetime": "2025-02-07T20:20:46.285944+08:00"
}